popexposure/__init__.py
popexposure/pop_estimator.py
popexposure/utils/__init__.py
popexposure/utils/geom_ops.py
popexposure/utils/geom_validator.py
popexposure/utils/mask_raster_partial_pixel.py
popexposure/utils/reader.py
popexposure-1.0.0.dev18.dist-info/LICENSE
popexposure-1.0.0.dev18.dist-info/METADATA
popexposure-1.0.0.dev18.dist-info/WHEEL
popexposure-1.0.0.dev18.dist-info/RECORD
