Metadata-Version: 2.3
Name: popexposure
Version: 1.0.0.dev18
Summary: A package for finding the number of people residing near environmental hazards
License: MIT
Keywords: population,exposure,wildfires,environmental,hazards,climate,exposed
Author: heathermcb
Author-email: heathermcbrien2.0@gmail.com
Requires-Python: >=3.11
Classifier: Programming Language :: Python :: 3
Classifier: Operating System :: OS Independent
Classifier: License :: OSI Approved :: MIT License
Classifier: Development Status :: 4 - Beta
Classifier: Intended Audience :: Developers
Classifier: Topic :: Software Development :: Libraries :: Python Modules
Requires-Dist: affine
Requires-Dist: exactextract
Requires-Dist: geopandas (==1.0.1)
Requires-Dist: matplotlib
Requires-Dist: numpy (==2.0.1)
Requires-Dist: pandas
Requires-Dist: pyarrow
Requires-Dist: pyproj
Requires-Dist: rasterio
Requires-Dist: scipy (>=1.10,<1.15)
Requires-Dist: shapely
Requires-Dist: tqdm
Project-URL: Documentation, https://github.com/heathermcb/popexposure#readme
Project-URL: Homepage, https://github.com/heathermcb/popexposure
Project-URL: Source, https://github.com/heathermcb/popexposure
